<?xml version="1.0" encoding="utf-8"?>
<SoundBanksInfo Platform="Mac" BasePlatform="Mac" SchemaVersion="16" SoundBankVersion="150">
	<RootPaths>
		<ProjectRoot>../..</ProjectRoot>
		<SourceFilesRoot>../../.cache/Mac</SourceFilesRoot>
		<SoundBanksRoot>.</SoundBanksRoot>
		<ExternalSourcesInputFile></ExternalSourcesInputFile>
		<ExternalSourcesOutputRoot>.</ExternalSourcesOutputRoot>
	</RootPaths>
	<DialogueEvents/>
	<SoundBanks>
		<SoundBank Id="1355168291" Type="User" GUID="{701ECBBD-9C7B-4030-8CDB-749EE5D1C7B9}" Language="SFX" Hash="{42B73830-ED9F-1A64-096E-9501E2ACB758}">
			<ObjectPath>Init</ObjectPath>
			<ShortName>Init</ShortName>
			<Path>Init.bnk</Path>
			<Plugins>
				<AudioDevices>
					<Plugin Id="2317455096" Name="No_Output" ObjectPath="\Audio Devices\Default Work Unit\No_Output" GUID="{E9E30709-220F-4EB7-83B4-0D198BFBAF41}" LibName="No Output" LibId="11862023"/>
					<Plugin Id="3859886410" Name="System" ObjectPath="\Audio Devices\Default Work Unit\System" GUID="{7777B3DF-3037-4128-AA9A-92FD938A9C54}" LibName="System" LibId="11403271"/>
				</AudioDevices>
			</Plugins>
			<Busses>
				<Bus Id="77978275" Name="Ambient" ObjectPath="\Master-Mixer Hierarchy\Default Work Unit\Master Audio Bus\World\Ambient" GUID="{2D564CC9-E363-4BFD-944E-675183F86EE2}"/>
				<Bus Id="838047381" Name="Non-World" ObjectPath="\Master-Mixer Hierarchy\Default Work Unit\Master Audio Bus\Non-World" GUID="{90609A59-335F-465C-99C3-C794D2B4BAE1}"/>
				<Bus Id="1069431850" Name="Player" ObjectPath="\Master-Mixer Hierarchy\Default Work Unit\Master Audio Bus\World\Player" GUID="{CA9292FC-A468-4D20-BCEF-604E0BE0E80B}"/>
				<Bus Id="1551306167" Name="UI" ObjectPath="\Master-Mixer Hierarchy\Default Work Unit\Master Audio Bus\Non-World\UI" GUID="{4EECB82E-49C5-4DE1-8066-61AA614F0A2D}"/>
				<Bus Id="2609808943" Name="World" ObjectPath="\Master-Mixer Hierarchy\Default Work Unit\Master Audio Bus\World" GUID="{C323AC67-8B58-4B15-AFCF-2E1D815878EA}"/>
				<Bus Id="3055412916" Name="Object" ObjectPath="\Master-Mixer Hierarchy\Default Work Unit\Master Audio Bus\World\Object" GUID="{55B1A578-914D-462D-BEBE-4F39791180C0}"/>
				<Bus Id="3803692087" Name="Master Audio Bus" ObjectPath="\Master-Mixer Hierarchy\Default Work Unit\Master Audio Bus" GUID="{1514A4D8-1DA6-412A-A17E-75CA0C2149F3}"/>
				<Bus Id="3991942870" Name="Music" ObjectPath="\Master-Mixer Hierarchy\Default Work Unit\Master Audio Bus\Non-World\Music" GUID="{9FFAAD1A-AE42-4880-B099-904E146BF8CF}"/>
			</Busses>
			<GameParameters>
				<GameParameter Id="804423979" Name="Whole_Volume" ObjectPath="\Game Parameters\Default Work Unit\Whole_Volume" GUID="{D8A0AA7D-7984-419C-A9FB-891341CEC896}"/>
				<GameParameter Id="822163944" Name="SS_Air_RPM" ObjectPath="\Game Parameters\Factory Soundseed Air Game Syncs\SS_Air_RPM" GUID="{A34890AB-B9D5-4526-A64D-5290C43EF2DC}"/>
				<GameParameter Id="1006694123" Name="Music_Volume" ObjectPath="\Game Parameters\Default Work Unit\Music_Volume" GUID="{921CA196-A70A-4ED1-BFFF-0576E0FFEE87}"/>
				<GameParameter Id="1029930033" Name="SS_Air_Fury" ObjectPath="\Game Parameters\Factory Soundseed Air Game Syncs\SS_Air_Fury" GUID="{A2AE79DC-CA3A-46BA-9652-9986C322A87B}"/>
				<GameParameter Id="1268619444" Name="Award" ObjectPath="\Game Parameters\Default Work Unit\Award" GUID="{84D4851D-85DC-4216-B9C0-2741AB2FE7C6}"/>
				<GameParameter Id="1351367891" Name="SS_Air_Fear" ObjectPath="\Game Parameters\Factory Soundseed Air Game Syncs\SS_Air_Fear" GUID="{F72E0659-4346-4E1C-A1B1-DAB46A05101E}"/>
				<GameParameter Id="1564184899" Name="SFX_Volume" ObjectPath="\Game Parameters\Default Work Unit\SFX_Volume" GUID="{49A03EC9-CDF7-4D57-806E-2B50978C317C}"/>
				<GameParameter Id="2648548617" Name="SS_Air_Month" ObjectPath="\Game Parameters\Factory Soundseed Air Game Syncs\SS_Air_Month" GUID="{09E2B445-C4A3-447F-B3CA-818A1D925EF7}"/>
				<GameParameter Id="3002758120" Name="SS_Air_Freefall" ObjectPath="\Game Parameters\Factory Soundseed Air Game Syncs\SS_Air_Freefall" GUID="{2F2DFE37-4F9E-4D94-83D8-53CCA39781AD}"/>
				<GameParameter Id="3074696722" Name="SS_Air_Size" ObjectPath="\Game Parameters\Factory Soundseed Air Game Syncs\SS_Air_Size" GUID="{1329EBEF-A193-472E-A38C-64668B494879}"/>
				<GameParameter Id="3203397129" Name="SS_Air_TimeOfDay" ObjectPath="\Game Parameters\Factory Soundseed Air Game Syncs\SS_Air_TimeOfDay" GUID="{536FA72C-8C7E-4C8B-AE03-EF34FDADC314}"/>
				<GameParameter Id="3715662592" Name="SS_Air_Storm" ObjectPath="\Game Parameters\Factory Soundseed Air Game Syncs\SS_Air_Storm" GUID="{E93F8CDB-06D1-4737-ACAF-7CD44BBED783}"/>
				<GameParameter Id="3847924954" Name="SS_Air_Presence" ObjectPath="\Game Parameters\Factory Soundseed Air Game Syncs\SS_Air_Presence" GUID="{E3B7811A-7B2F-490F-B44F-5FE51B468041}"/>
				<GameParameter Id="4160247818" Name="SS_Air_Turbulence" ObjectPath="\Game Parameters\Factory Soundseed Air Game Syncs\SS_Air_Turbulence" GUID="{EDA87B19-73AA-40A0-9F19-2073606DB710}"/>
			</GameParameters>
			<AcousticTextures>
				<AcousticTexture Id="504532776" Name="Brick" ObjectPath="\Virtual Acoustics\Factory Acoustic Textures\Textures\Brick" GUID="{B086A5A9-F204-4C53-A838-BDB18B18F6D6}">
					<Properties>
						<Property Name="AbsorptionLow" Type="Real32" Value="12"/>
						<Property Name="AbsorptionMidLow" Type="Real32" Value="18"/>
						<Property Name="AbsorptionMidHigh" Type="Real32" Value="23"/>
						<Property Name="AbsorptionHigh" Type="Real32" Value="35"/>
						<Property Name="Scattering" Type="Real32" Value="0"/>
					</Properties>
				</AcousticTexture>
				<AcousticTexture Id="513139656" Name="Mountain" ObjectPath="\Virtual Acoustics\Factory Acoustic Textures\Textures\Mountain" GUID="{C5933731-001A-4AB4-98DD-9B033A8C8EAB}">
					<Properties>
						<Property Name="AbsorptionLow" Type="Real32" Value="0"/>
						<Property Name="AbsorptionMidLow" Type="Real32" Value="0"/>
						<Property Name="AbsorptionMidHigh" Type="Real32" Value="0"/>
						<Property Name="AbsorptionHigh" Type="Real32" Value="0"/>
						<Property Name="Scattering" Type="Real32" Value="0"/>
					</Properties>
				</AcousticTexture>
				<AcousticTexture Id="841620460" Name="Concrete" ObjectPath="\Virtual Acoustics\Factory Acoustic Textures\Textures\Concrete" GUID="{5CF81C00-2896-4AE0-AF7C-3080BDABA682}">
					<Properties>
						<Property Name="AbsorptionLow" Type="Real32" Value="6"/>
						<Property Name="AbsorptionMidLow" Type="Real32" Value="6"/>
						<Property Name="AbsorptionMidHigh" Type="Real32" Value="6"/>
						<Property Name="AbsorptionHigh" Type="Real32" Value="14"/>
						<Property Name="Scattering" Type="Real32" Value="0"/>
					</Properties>
				</AcousticTexture>
				<AcousticTexture Id="1755085759" Name="Wood_Deep" ObjectPath="\Virtual Acoustics\Factory Acoustic Textures\Textures\Wood_Deep" GUID="{5246478E-C5DA-4E0C-A0DE-C98D1479529A}">
					<Properties>
						<Property Name="AbsorptionLow" Type="Real32" Value="1"/>
						<Property Name="AbsorptionMidLow" Type="Real32" Value="8"/>
						<Property Name="AbsorptionMidHigh" Type="Real32" Value="20"/>
						<Property Name="AbsorptionHigh" Type="Real32" Value="35"/>
						<Property Name="Scattering" Type="Real32" Value="0"/>
					</Properties>
				</AcousticTexture>
				<AcousticTexture Id="1873957695" Name="Anechoic" ObjectPath="\Virtual Acoustics\Factory Acoustic Textures\Textures\Anechoic" GUID="{8B0AC232-02E2-4EDE-BEAC-FDD1A900E3ED}">
					<Properties>
						<Property Name="AbsorptionLow" Type="Real32" Value="100"/>
						<Property Name="AbsorptionMidLow" Type="Real32" Value="100"/>
						<Property Name="AbsorptionMidHigh" Type="Real32" Value="100"/>
						<Property Name="AbsorptionHigh" Type="Real32" Value="100"/>
						<Property Name="Scattering" Type="Real32" Value="0"/>
					</Properties>
				</AcousticTexture>
				<AcousticTexture Id="1970351858" Name="Fabric" ObjectPath="\Virtual Acoustics\Factory Acoustic Textures\Textures\Fabric" GUID="{8381D532-DB6E-4EED-A7A3-BC7B0A0B8BA8}">
					<Properties>
						<Property Name="AbsorptionLow" Type="Real32" Value="3"/>
						<Property Name="AbsorptionMidLow" Type="Real32" Value="13"/>
						<Property Name="AbsorptionMidHigh" Type="Real32" Value="48"/>
						<Property Name="AbsorptionHigh" Type="Real32" Value="72"/>
						<Property Name="Scattering" Type="Real32" Value="0"/>
					</Properties>
				</AcousticTexture>
				<AcousticTexture Id="2058049674" Name="Wood" ObjectPath="\Virtual Acoustics\Factory Acoustic Textures\Textures\Wood" GUID="{1FFFBC96-6FE7-489E-BA6C-7C14A71391AE}">
					<Properties>
						<Property Name="AbsorptionLow" Type="Real32" Value="32"/>
						<Property Name="AbsorptionMidLow" Type="Real32" Value="25"/>
						<Property Name="AbsorptionMidHigh" Type="Real32" Value="20"/>
						<Property Name="AbsorptionHigh" Type="Real32" Value="35"/>
						<Property Name="Scattering" Type="Real32" Value="0"/>
					</Properties>
				</AcousticTexture>
				<AcousticTexture Id="2412606308" Name="Carpet" ObjectPath="\Virtual Acoustics\Factory Acoustic Textures\Textures\Carpet" GUID="{34227589-DC56-4260-96C4-B9F4B669092B}">
					<Properties>
						<Property Name="AbsorptionLow" Type="Real32" Value="46"/>
						<Property Name="AbsorptionMidLow" Type="Real32" Value="45"/>
						<Property Name="AbsorptionMidHigh" Type="Real32" Value="76"/>
						<Property Name="AbsorptionHigh" Type="Real32" Value="100"/>
						<Property Name="Scattering" Type="Real32" Value="0"/>
					</Properties>
				</AcousticTexture>
				<AcousticTexture Id="2637588553" Name="Tile" ObjectPath="\Virtual Acoustics\Factory Acoustic Textures\Textures\Tile" GUID="{A882DAC4-132A-47B7-BA9D-B9907BA29CC0}">
					<Properties>
						<Property Name="AbsorptionLow" Type="Real32" Value="67"/>
						<Property Name="AbsorptionMidLow" Type="Real32" Value="41"/>
						<Property Name="AbsorptionMidHigh" Type="Real32" Value="12"/>
						<Property Name="AbsorptionHigh" Type="Real32" Value="0"/>
						<Property Name="Scattering" Type="Real32" Value="0"/>
					</Properties>
				</AcousticTexture>
				<AcousticTexture Id="2928161104" Name="Curtains" ObjectPath="\Virtual Acoustics\Factory Acoustic Textures\Textures\Curtains" GUID="{F8E69E33-5C97-4968-B508-A1535F2D66E8}">
					<Properties>
						<Property Name="AbsorptionLow" Type="Real32" Value="7"/>
						<Property Name="AbsorptionMidLow" Type="Real32" Value="60"/>
						<Property Name="AbsorptionMidHigh" Type="Real32" Value="0"/>
						<Property Name="AbsorptionHigh" Type="Real32" Value="84"/>
						<Property Name="Scattering" Type="Real32" Value="0"/>
					</Properties>
				</AcousticTexture>
				<AcousticTexture Id="3195498748" Name="Cork_Tiles" ObjectPath="\Virtual Acoustics\Factory Acoustic Textures\Textures\Cork_Tiles" GUID="{30D2C919-925F-4143-8906-3DBB3C4AE5E2}">
					<Properties>
						<Property Name="AbsorptionLow" Type="Real32" Value="14"/>
						<Property Name="AbsorptionMidLow" Type="Real32" Value="30"/>
						<Property Name="AbsorptionMidHigh" Type="Real32" Value="73"/>
						<Property Name="AbsorptionHigh" Type="Real32" Value="100"/>
						<Property Name="Scattering" Type="Real32" Value="0"/>
					</Properties>
				</AcousticTexture>
				<AcousticTexture Id="3670307564" Name="Drywall" ObjectPath="\Virtual Acoustics\Factory Acoustic Textures\Textures\Drywall" GUID="{68A4E3F4-4C0B-4687-A8B8-A84DB93DBC8F}">
					<Properties>
						<Property Name="AbsorptionLow" Type="Real32" Value="2"/>
						<Property Name="AbsorptionMidLow" Type="Real32" Value="2"/>
						<Property Name="AbsorptionMidHigh" Type="Real32" Value="2"/>
						<Property Name="AbsorptionHigh" Type="Real32" Value="2"/>
						<Property Name="Scattering" Type="Real32" Value="0"/>
					</Properties>
				</AcousticTexture>
				<AcousticTexture Id="4168643977" Name="Acoustic_Banner" ObjectPath="\Virtual Acoustics\Factory Acoustic Textures\Textures\Acoustic_Banner" GUID="{2F2D53F2-DACC-408E-8B88-98B1B52A26D6}">
					<Properties>
						<Property Name="AbsorptionLow" Type="Real32" Value="37"/>
						<Property Name="AbsorptionMidLow" Type="Real32" Value="100"/>
						<Property Name="AbsorptionMidHigh" Type="Real32" Value="100"/>
						<Property Name="AbsorptionHigh" Type="Real32" Value="100"/>
						<Property Name="Scattering" Type="Real32" Value="0"/>
					</Properties>
				</AcousticTexture>
				<AcousticTexture Id="4262522749" Name="Wood_Bright" ObjectPath="\Virtual Acoustics\Factory Acoustic Textures\Textures\Wood_Bright" GUID="{7B85D1E5-C1A2-4E63-9A13-CEC54B641ADC}">
					<Properties>
						<Property Name="AbsorptionLow" Type="Real32" Value="32"/>
						<Property Name="AbsorptionMidLow" Type="Real32" Value="25"/>
						<Property Name="AbsorptionMidHigh" Type="Real32" Value="10"/>
						<Property Name="AbsorptionHigh" Type="Real32" Value="9"/>
						<Property Name="Scattering" Type="Real32" Value="0"/>
					</Properties>
				</AcousticTexture>
			</AcousticTextures>
		</SoundBank>
		<SoundBank Id="3161908922" Type="User" GUID="{DBA25B59-2100-43A4-B1D1-ABCEB2AF0139}" Language="SFX" Hash="{09D9378B-B2F3-9422-A650-E9B6B11E3F82}">
			<ObjectPath>\SoundBanks\Default Work Unit\Main</ObjectPath>
			<ShortName>Main</ShortName>
			<Path>Main.bnk</Path>
			<Media>
				<File Id="1725109" Language="SFX" Streaming="false" Location="Memory">
					<ShortName>Ambient_LoomWork_Gear_01.wav</ShortName>
					<CachePath>SFX/Ambient_LoomWork_Gear_01_C4BEA434.wem</CachePath>
				</File>
				<File Id="71231233" Language="SFX" Streaming="false" Location="Memory">
					<ShortName>Ambient_HouseMoan_Wood_07.wav</ShortName>
					<CachePath>SFX/Ambient_HouseMoan_Wood_07_818F3B66.wem</CachePath>
				</File>
				<File Id="118663403" Language="SFX" Streaming="false" Location="Memory">
					<ShortName>Object_Order_Appear_01.wav</ShortName>
					<CachePath>SFX/Object_Order_Appear_01_818F3B66.wem</CachePath>
				</File>
				<File Id="131515225" Language="SFX" Streaming="false" Location="Memory">
					<ShortName>UI_Game_Award_01.wav</ShortName>
					<CachePath>SFX/UI_Game_Award_01_818F3B66.wem</CachePath>
				</File>
				<File Id="139513863" Language="SFX" Streaming="false" Location="Memory">
					<ShortName>Ambient_HouseMoan_Wood_05.wav</ShortName>
					<CachePath>SFX/Ambient_HouseMoan_Wood_05_818F3B66.wem</CachePath>
				</File>
				<File Id="141710736" Language="SFX" Streaming="false" Location="Memory">
					<ShortName>UI_Game_Win_01.wav</ShortName>
					<CachePath>SFX/UI_Game_Win_01_818F3B66.wem</CachePath>
				</File>
				<File Id="180774633" Language="SFX" Streaming="false" Location="Memory">
					<ShortName>UI_Game_Fail_01.wav</ShortName>
					<CachePath>SFX/UI_Game_Fail_01_818F3B66.wem</CachePath>
				</File>
				<File Id="213425621" Language="SFX" Streaming="false" Location="Memory">
					<ShortName>Ambient_HouseMoan_Wood_06.wav</ShortName>
					<CachePath>SFX/Ambient_HouseMoan_Wood_06_818F3B66.wem</CachePath>
				</File>
				<File Id="221294234" Language="SFX" Streaming="false" Location="Memory">
					<ShortName>Player_Grab_01.wav</ShortName>
					<CachePath>SFX/Player_Grab_01_818F3B66.wem</CachePath>
				</File>
				<File Id="308571478" Language="SFX" Streaming="false" Location="Memory">
					<ShortName>Player_Move_03.wav</ShortName>
					<CachePath>SFX/Player_Move_03_818F3B66.wem</CachePath>
				</File>
				<File Id="364255195" Language="SFX" Streaming="false" Location="Memory">
					<ShortName>Ambient_LoomWork_Flying_01.wav</ShortName>
					<CachePath>SFX/Ambient_LoomWork_Flying_01_0C10528E.wem</CachePath>
				</File>
				<File Id="370357429" Language="SFX" Streaming="false" Location="Memory">
					<ShortName>Ambient_HouseMoan_Ambience_01.wav</ShortName>
					<CachePath>SFX/Ambient_HouseMoan_Ambience_01_77674B82.wem</CachePath>
				</File>
				<File Id="393325668" Language="SFX" Streaming="false" Location="Memory">
					<ShortName>Object_Order_Finish_01.wav</ShortName>
					<CachePath>SFX/Object_Order_Finish_01_818F3B66.wem</CachePath>
				</File>
				<File Id="463857265" Language="SFX" Streaming="false" Location="Memory">
					<ShortName>Ambient_GrandmaWork_01.wav</ShortName>
					<CachePath>SFX/Ambient_GrandmaWork_01_7D980A4E.wem</CachePath>
				</File>
				<File Id="484607081" Language="SFX" Streaming="false" Location="Memory">
					<ShortName>Player_Drop_01.wav</ShortName>
					<CachePath>SFX/Player_Drop_01_818F3B66.wem</CachePath>
				</File>
				<File Id="525799224" Language="SFX" Streaming="false" Location="Memory">
					<ShortName>Object_Order_Miss_01.wav</ShortName>
					<CachePath>SFX/Object_Order_Miss_01_818F3B66.wem</CachePath>
				</File>
				<File Id="620050953" Language="SFX" Streaming="false" Location="Memory">
					<ShortName>Player_Move_04.wav</ShortName>
					<CachePath>SFX/Player_Move_04_818F3B66.wem</CachePath>
				</File>
				<File Id="635490974" Language="SFX" Streaming="false" Location="Memory">
					<ShortName>Ambient_HouseMoan_Wood_03.wav</ShortName>
					<CachePath>SFX/Ambient_HouseMoan_Wood_03_818F3B66.wem</CachePath>
				</File>
				<File Id="637497874" Language="SFX" Streaming="false" Location="Memory">
					<ShortName>Player_Move_05.wav</ShortName>
					<CachePath>SFX/Player_Move_05_818F3B66.wem</CachePath>
				</File>
				<File Id="686526134" Language="SFX" Streaming="false" Location="Memory">
					<ShortName>UI_Game_Begin_01.wav</ShortName>
					<CachePath>SFX/UI_Game_Begin_01_818F3B66.wem</CachePath>
				</File>
				<File Id="707589975" Language="SFX" Streaming="false" Location="Memory">
					<ShortName>Player_Move_01.wav</ShortName>
					<CachePath>SFX/Player_Move_01_818F3B66.wem</CachePath>
				</File>
				<File Id="720499055" Language="SFX" Streaming="false" Location="Memory">
					<ShortName>Ambient_HouseMoan_Wood_04.wav</ShortName>
					<CachePath>SFX/Ambient_HouseMoan_Wood_04_818F3B66.wem</CachePath>
				</File>
				<File Id="835353441" Language="SFX" Streaming="false" Location="Memory">
					<ShortName>Ambient_HouseMoan_Wood_01.wav</ShortName>
					<CachePath>SFX/Ambient_HouseMoan_Wood_01_818F3B66.wem</CachePath>
				</File>
				<File Id="851191821" Language="SFX" Streaming="false" Location="Memory">
					<ShortName>UI_Confirm_01.wav</ShortName>
					<CachePath>SFX/UI_Confirm_01_818F3B66.wem</CachePath>
				</File>
				<File Id="875001955" Language="SFX" Streaming="false" Location="Memory">
					<ShortName>Object_Loom_Change_01.wav</ShortName>
					<CachePath>SFX/Object_Loom_Change_01_818F3B66.wem</CachePath>
				</File>
				<File Id="896426213" Language="SFX" Streaming="false" Location="Memory">
					<ShortName>Object_Order_Move_01.wav</ShortName>
					<CachePath>SFX/Object_Order_Move_01_818F3B66.wem</CachePath>
				</File>
				<File Id="1004740522" Language="SFX" Streaming="false" Location="Memory">
					<ShortName>Object_Loom_Finish_01.wav</ShortName>
					<CachePath>SFX/Object_Loom_Finish_01_818F3B66.wem</CachePath>
				</File>
				<File Id="1008495583" Language="SFX" Streaming="false" Location="Memory">
					<ShortName>Ambient_HouseMoan_Wood_02.wav</ShortName>
					<CachePath>SFX/Ambient_HouseMoan_Wood_02_818F3B66.wem</CachePath>
				</File>
				<File Id="1048008292" Language="SFX" Streaming="false" Location="Memory">
					<ShortName>Player_Move_02.wav</ShortName>
					<CachePath>SFX/Player_Move_02_818F3B66.wem</CachePath>
				</File>
				<File Id="1071958468" Language="SFX" Streaming="false" Location="Memory">
					<ShortName>Ambient_MachineWork_01.wav</ShortName>
					<CachePath>SFX/Ambient_MachineWork_01_8F41B513.wem</CachePath>
				</File>
			</Media>
			<Events>
				<Event Id="934150494" Name="Ambient_GrandmaWork_Play" ObjectPath="\Events\Default Work Unit\World\Ambient\Ambient_GrandmaWork\Ambient_GrandmaWork_Play" GUID="{3C781E50-1247-4946-9ED3-056C809309EA}" DurationType="Infinite">
					<MediaRefs>
						<MediaRef Id="463857265"/>
					</MediaRefs>
				</Event>
				<Event Id="1972146464" Name="Ambient_GrandmaWork_Stop" ObjectPath="\Events\Default Work Unit\World\Ambient\Ambient_GrandmaWork\Ambient_GrandmaWork_Stop" GUID="{13FCB0CB-5CB1-4905-8602-FB697ED1D555}" MaxAttenuation="0" DurationType="OneShot" DurationMin="0" DurationMax="0"/>
				<Event Id="1759941420" Name="Ambient_HouseMoan_Play" ObjectPath="\Events\Default Work Unit\World\Ambient\Ambient_HouseMoan\Ambient_HouseMoan_Play" GUID="{FFB30B91-853A-47F9-9C70-7C0FEEEA8CD3}" DurationType="Infinite">
					<MediaRefs>
						<MediaRef Id="71231233"/>
						<MediaRef Id="139513863"/>
						<MediaRef Id="213425621"/>
						<MediaRef Id="370357429"/>
						<MediaRef Id="635490974"/>
						<MediaRef Id="720499055"/>
						<MediaRef Id="835353441"/>
						<MediaRef Id="1008495583"/>
					</MediaRefs>
				</Event>
				<Event Id="3729726006" Name="Ambient_HouseMoan_Stop" ObjectPath="\Events\Default Work Unit\World\Ambient\Ambient_HouseMoan\Ambient_HouseMoan_Stop" GUID="{A1E6AC24-F366-41A2-B819-2B47614842E7}" MaxAttenuation="0" DurationType="OneShot" DurationMin="0" DurationMax="0"/>
				<Event Id="1515509559" Name="Ambient_LoomWork_Play" ObjectPath="\Events\Default Work Unit\World\Ambient\Ambient_LoomWork\Ambient_LoomWork_Play" GUID="{7FE280C5-8244-46E2-B1DE-8ABC6DFC5265}" DurationType="Infinite">
					<MediaRefs>
						<MediaRef Id="1725109"/>
						<MediaRef Id="364255195"/>
					</MediaRefs>
				</Event>
				<Event Id="245528677" Name="Ambient_LoomWork_Stop" ObjectPath="\Events\Default Work Unit\World\Ambient\Ambient_LoomWork\Ambient_LoomWork_Stop" GUID="{04BF3529-6E74-4E4B-80B3-072C231223BD}" MaxAttenuation="0" DurationType="OneShot" DurationMin="0" DurationMax="0"/>
				<Event Id="2741153787" Name="Ambient_MachineWork_Play" ObjectPath="\Events\Default Work Unit\World\Ambient\Ambient_MachineWork\Ambient_MachineWork_Play" GUID="{F5E3DB2F-4E98-4AD0-B512-6129BE495730}" DurationType="Infinite">
					<MediaRefs>
						<MediaRef Id="1071958468"/>
					</MediaRefs>
				</Event>
				<Event Id="1610616497" Name="Ambient_MachineWork_Stop" ObjectPath="\Events\Default Work Unit\World\Ambient\Ambient_MachineWork\Ambient_MachineWork_Stop" GUID="{3D7F9E43-180C-4812-ABFD-E7CE9F655CC5}" MaxAttenuation="0" DurationType="OneShot" DurationMin="0" DurationMax="0"/>
				<Event Id="15273518" Name="Music_Explore" ObjectPath="\Events\Default Work Unit\Non-World\Music\Music_Explore" GUID="{981D46BA-2BA9-444F-B450-AA08D65176DB}" DurationType="OneShot" DurationMin="0" DurationMax="0"/>
				<Event Id="3227181061" Name="Music_Stop" ObjectPath="\Events\Default Work Unit\Non-World\Music\Music_Stop" GUID="{9F800CC9-2F27-44E2-909C-2E16ADA90CA9}" MaxAttenuation="0" DurationType="OneShot" DurationMin="0" DurationMax="0"/>
				<Event Id="2456972663" Name="Object_Loom_Change" ObjectPath="\Events\Default Work Unit\World\Object\Object_Loom\Object_Loom_Change" GUID="{A4905E33-0A1F-4090-94C1-43107D9AB6C0}" DurationType="OneShot" DurationMin="0.93362814" DurationMax="0.93362814">
					<MediaRefs>
						<MediaRef Id="875001955"/>
					</MediaRefs>
				</Event>
				<Event Id="631574478" Name="Object_Loom_Finish" ObjectPath="\Events\Default Work Unit\World\Object\Object_Loom\Object_Loom_Finish" GUID="{ADB2F618-CE13-466C-96A6-823908A53278}" DurationType="OneShot" DurationMin="1.5165759" DurationMax="1.5165759">
					<MediaRefs>
						<MediaRef Id="1004740522"/>
					</MediaRefs>
				</Event>
				<Event Id="3575323535" Name="Object_Order_Appear" ObjectPath="\Events\Default Work Unit\World\Object\Object_Order\Object_Order_Appear" GUID="{E94B3039-AA06-4760-AA59-6427D3B8B397}" DurationType="OneShot" DurationMin="1.9926984" DurationMax="1.9926984">
					<MediaRefs>
						<MediaRef Id="118663403"/>
					</MediaRefs>
				</Event>
				<Event Id="2774872329" Name="Object_Order_Finish" ObjectPath="\Events\Default Work Unit\World\Object\Object_Order\Object_Order_Finish" GUID="{2D698B31-9D21-465B-B82C-D53436A075A5}" DurationType="OneShot" DurationMin="0.998458" DurationMax="0.998458">
					<MediaRefs>
						<MediaRef Id="393325668"/>
					</MediaRefs>
				</Event>
				<Event Id="3259942628" Name="Object_Order_Miss" ObjectPath="\Events\Default Work Unit\World\Object\Object_Order\Object_Order_Miss" GUID="{D3839204-CB6A-42EC-AD2C-2BF98FDCF298}" DurationType="OneShot" DurationMin="4" DurationMax="4">
					<MediaRefs>
						<MediaRef Id="525799224"/>
					</MediaRefs>
				</Event>
				<Event Id="2907906771" Name="Object_Order_Move" ObjectPath="\Events\Default Work Unit\World\Object\Object_Order\Object_Order_Move" GUID="{70A3C123-BC20-4926-9297-E41D0B0BF75E}" DurationType="OneShot" DurationMin="0.9929478" DurationMax="0.9929478">
					<MediaRefs>
						<MediaRef Id="896426213"/>
					</MediaRefs>
				</Event>
				<Event Id="1922690190" Name="Player_Drop" ObjectPath="\Events\Default Work Unit\World\Player\Player_Drop" GUID="{46D336C7-8A8C-4FEE-9367-68FBFAB36DF6}" DurationType="OneShot" DurationMin="1.028322" DurationMax="1.028322">
					<MediaRefs>
						<MediaRef Id="484607081"/>
					</MediaRefs>
				</Event>
				<Event Id="816303795" Name="Player_Grab" ObjectPath="\Events\Default Work Unit\World\Player\Player_Grab" GUID="{CB607481-B711-4490-88C4-BB9432CD8397}" DurationType="OneShot" DurationMin="1.1348526" DurationMax="1.1348526">
					<MediaRefs>
						<MediaRef Id="221294234"/>
					</MediaRefs>
				</Event>
				<Event Id="2248092158" Name="Player_Move" ObjectPath="\Events\Default Work Unit\World\Player\Player_Move" GUID="{1CAF2757-238F-480F-9333-CE900DDDA91E}" DurationType="Infinite">
					<MediaRefs>
						<MediaRef Id="308571478"/>
						<MediaRef Id="620050953"/>
						<MediaRef Id="637497874"/>
						<MediaRef Id="707589975"/>
						<MediaRef Id="1048008292"/>
					</MediaRefs>
				</Event>
				<Event Id="3361170585" Name="Player_Stop" ObjectPath="\Events\Default Work Unit\World\Player\Player_Stop" GUID="{4622741F-3C08-436B-B1E5-CF87A97441BF}" MaxAttenuation="0" DurationType="OneShot" DurationMin="0" DurationMax="0"/>
				<Event Id="452547817" Name="STOP_ALL" ObjectPath="\Events\Default Work Unit\STOP_ALL" GUID="{67FA17D0-8D6C-4E27-9BD6-3D97DFA791F0}" MaxAttenuation="0" DurationType="OneShot" DurationMin="0" DurationMax="0"/>
				<Event Id="216067002" Name="UI_Confirm" ObjectPath="\Events\Default Work Unit\Non-World\UI\UI_Confirm" GUID="{53EA3260-46FA-4100-AAA1-EC992F9A0D83}" DurationType="OneShot" DurationMin="0.45850202" DurationMax="0.5452539">
					<MediaRefs>
						<MediaRef Id="851191821"/>
					</MediaRefs>
				</Event>
				<Event Id="1653993118" Name="UI_Game_Award" ObjectPath="\Events\Default Work Unit\Non-World\UI\UI_Game\UI_Game_Award" GUID="{230F88E3-F322-4B57-BA45-C1BA4C288441}" DurationType="OneShot" DurationMin="1.5" DurationMax="1.5">
					<MediaRefs>
						<MediaRef Id="131515225"/>
					</MediaRefs>
				</Event>
				<Event Id="921872670" Name="UI_Game_Begin" ObjectPath="\Events\Default Work Unit\Non-World\UI\UI_Game\UI_Game_Begin" GUID="{3E7D6172-0CE0-464A-AEB0-D22DCC8C37C9}" DurationType="OneShot" DurationMin="3.5339909" DurationMax="3.5339909">
					<MediaRefs>
						<MediaRef Id="686526134"/>
					</MediaRefs>
				</Event>
				<Event Id="150810275" Name="UI_Game_Fail" ObjectPath="\Events\Default Work Unit\Non-World\UI\UI_Game\UI_Game_Fail" GUID="{A93513BC-270D-4452-BADE-930632BEB393}" DurationType="OneShot" DurationMin="1.9811338" DurationMax="1.9811338">
					<MediaRefs>
						<MediaRef Id="180774633"/>
					</MediaRefs>
				</Event>
				<Event Id="380860655" Name="UI_Game_Win" ObjectPath="\Events\Default Work Unit\Non-World\UI\UI_Game\UI_Game_Win" GUID="{CD7106AD-2C59-4CB2-A968-590DE9123D88}" DurationType="OneShot" DurationMin="3" DurationMax="3">
					<MediaRefs>
						<MediaRef Id="141710736"/>
					</MediaRefs>
				</Event>
			</Events>
		</SoundBank>
	</SoundBanks>
	<FileHash>{D812A6AC-856D-0B11-8B18-21DA09B3D376}</FileHash>
</SoundBanksInfo>
